pylookout/__init__.py
pylookout/__main__.py
pylookout/info_collector.py
pylookout/lookout.py
pylookout/lookout_cli.py
pylookout/notification_methods.py
pylookout-0.2.6.dist-info/LICENSE
pylookout-0.2.6.dist-info/METADATA
pylookout-0.2.6.dist-info/WHEEL
pylookout-0.2.6.dist-info/entry_points.txt
pylookout-0.2.6.dist-info/top_level.txt
pylookout-0.2.6.dist-info/RECORD
