Metadata-Version: 2.1
Name: pylookout
Version: 0.2.6
Summary: Simple Linux system monitoring tool
Home-page: https://github.com/Lab-Brat/pyLookout
Author: Lab-Brat
Author-email: labbrat_social@pm.me
License: MIT
Classifier: License :: OSI Approved :: MIT License
Classifier: Programming Language :: Python :: 3.10
Classifier: Operating System :: POSIX :: Linux
Requires-Python: >=3.6
License-File: LICENSE
Requires-Dist: psutil
Requires-Dist: click
Requires-Dist: sendgrid
